[
 {
  "app": "kaiten_erp",
  "charts": [],
  "content": "[{\"id\": \"amc_header_1\", \"type\": \"header\", \"data\": {\"text\": \"<span class=\\\"h4\\\"><b>AMC</b></span>\", \"col\": 12}}, {\"id\": \"amc_shortcut_1\", \"type\": \"shortcut\", \"data\": {\"shortcut_name\": \"Solar Site Profile\", \"col\": 4}}, {\"id\": \"amc_shortcut_2\", \"type\": \"shortcut\", \"data\": {\"shortcut_name\": \"AMC Contract\", \"col\": 4}}, {\"id\": \"amc_shortcut_3\", \"type\": \"shortcut\", \"data\": {\"shortcut_name\": \"Service Visit\", \"col\": 4}}, {\"id\": \"amc_shortcut_4\", \"type\": \"shortcut\", \"data\": {\"shortcut_name\": \"Complaint\", \"col\": 4}}, {\"id\": \"amc_shortcut_5\", \"type\": \"shortcut\", \"data\": {\"shortcut_name\": \"Renewal Notice\", \"col\": 4}}]",
  "custom_blocks": [],
  "docstatus": 0,
  "doctype": "Workspace",
  "external_link": null,
  "for_user": null,
  "hide_custom": 0,
  "icon": null,
  "indicator_color": null,
  "is_hidden": 0,
  "label": "AMC",
  "link_to": null,
  "link_type": null,
  "links": [
   {
    "dependencies": null,
    "description": null,
    "hidden": 0,
    "icon": null,
    "is_query_report": 0,
    "label": "Solar Site Profile",
    "link_count": 0,
    "link_to": "Solar Site Profile",
    "link_type": "DocType",
    "onboard": 1,
    "only_for": null,
    "report_ref_doctype": null,
    "type": "Link"
   },
   {
    "dependencies": null,
    "description": null,
    "hidden": 0,
    "icon": null,
    "is_query_report": 0,
    "label": "AMC Contract",
    "link_count": 0,
    "link_to": "AMC Contract",
    "link_type": "DocType",
    "onboard": 1,
    "only_for": null,
    "report_ref_doctype": null,
    "type": "Link"
   },
   {
    "dependencies": null,
    "description": null,
    "hidden": 0,
    "icon": null,
    "is_query_report": 0,
    "label": "Service Visit",
    "link_count": 0,
    "link_to": "Service Visit",
    "link_type": "DocType",
    "onboard": 1,
    "only_for": null,
    "report_ref_doctype": null,
    "type": "Link"
   },
   {
    "dependencies": null,
    "description": null,
    "hidden": 0,
    "icon": null,
    "is_query_report": 0,
    "label": "Complaint",
    "link_count": 0,
    "link_to": "Complaint",
    "link_type": "DocType",
    "onboard": 1,
    "only_for": null,
    "report_ref_doctype": null,
    "type": "Link"
   },
   {
    "dependencies": null,
    "description": null,
    "hidden": 0,
    "icon": null,
    "is_query_report": 0,
    "label": "Renewal Notice",
    "link_count": 0,
    "link_to": "Renewal Notice",
    "link_type": "DocType",
    "onboard": 0,
    "only_for": null,
    "report_ref_doctype": null,
    "type": "Link"
   }
  ],
  "modified": "2026-04-28 17:20:05.238877",
  "module": "AMC",
  "name": "AMC",
  "number_cards": [],
  "parent_page": null,
  "public": 1,
  "quick_lists": [],
  "restrict_to_domain": null,
  "roles": [],
  "sequence_id": 0.0,
  "shortcuts": [],
  "title": null,
  "type": null
 }
]